djangocms_education/__init__.py
djangocms_education/admin.py
djangocms_education/apps.py
djangocms_education/cms_plugins.py
djangocms_education/models.py
djangocms_education/tests.py
djangocms_education/views.py
djangocms_education/migrations/0001_initial.py
djangocms_education/migrations/0002_remove_education_title.py
djangocms_education/migrations/0003_education_end_date.py
djangocms_education/migrations/0004_alter_education_end_date.py
djangocms_education/migrations/__init__.py
djangocms_education/templates/djangocms_education/list_template.html
djangocms_education-1.7.0.dist-info/LICENSE
djangocms_education-1.7.0.dist-info/METADATA
djangocms_education-1.7.0.dist-info/WHEEL
djangocms_education-1.7.0.dist-info/top_level.txt
djangocms_education-1.7.0.dist-info/RECORD
