Metadata-Version: 2.1
Name: djangocms-education
Version: 1.7.0
Summary: Adds a Plugin for embedding your Resume to your website.
Home-page: https://github.com/crydotsnake/djangocms-education
Author: Simon Krull
Author-email: simon@django-cms.org
Maintainer: Simon Krull
Maintainer-email: simon@django-cms.org
License: BSD-3-Clause
Platform: UNKNOWN
License-File: LICENSE
Requires-Dist: django-cms (>=3.7)
Requires-Dist: djangocms-text-ckeditor (>=3.1.0)
Requires-Dist: python-dateutil (>=2.8.2)
